{
	"settingsTitle": "Ustawienia Emuchievements",
	"settingsGeneral": "Ogólne",
	"settingsApps": "Aplikacje",
	"settingsHideShortcuts": "Ukryj skróty",
	"settingsRetroAchievements": "RetroAchievements",
	"settingsInstructions": "Instrukcje",
	"settingsInstructionsMD": "Aby uzyskać klucz api, przejdź do [https://retroachievements.org/controlpanel.php](https://retroachievings. rg/controlpanel.php) i zaloguj się na swoje konto. Powinieneś zobaczyć swój klucz api w jednym z wpisów na tej stronie. Wpisz go w poniższym polu lub przejdź do trybu pulpitu i uruchom Steam w trybie Big Picture, dzięki czemu będziesz miał dostęp do schowka i wklej go,",
	"settingsUsername": "Nazwa użytkownika: ",
	"settingsAPIKey": "Klucz API: ",
	"loginSuccess": "Zalogowano pomyślnie",
	"loginFailed": "Błąd logowania",
	"settingsReset": "Settings JSON schema has changed, resetting JSON",
	"title": "Emuchievements",
	"settings": "Ustawienia",
	"achievements": "Osiągnięcia",
	"refresh": "Odśwież",
	"clear": "Clear Cache",
	"loading": "Ładowanie",
	"fetching": "Pobieranie",
	"error": "Error",
	"noAchievements": "Nie znaleziono osiągnięć",
	"foundAchievements": "Załadowano %%, Hash: %%",
	"noLogin": "Nie jesteś zalogowany! Zaloguj się, aby zobaczyć osiągnięcia."
}